PyFLOTRAN/__init__.py
PyFLOTRAN/config/__init__.py
PyFLOTRAN/config/conda_env.yml
PyFLOTRAN/config/config.yml
PyFLOTRAN/config/global_config.yml
PyFLOTRAN/config/logger_config.yml
PyFLOTRAN/interpolation/BaseInterpolator.py
PyFLOTRAN/interpolation/KdeEstimator.py
PyFLOTRAN/interpolation/SparseDataInterpolator.py
PyFLOTRAN/interpolation/__init__.py
PyFLOTRAN/paraview_processor/ParaviewProcessor.py
PyFLOTRAN/paraview_processor/__init__.py
PyFLOTRAN/paraview_processor/filters/AppendArcLengthFilter.py
PyFLOTRAN/paraview_processor/filters/BaseFilter.py
PyFLOTRAN/paraview_processor/filters/CalculatorFilter.py
PyFLOTRAN/paraview_processor/filters/CellDataToPointDataFilter.py
PyFLOTRAN/paraview_processor/filters/ClipFilter.py
PyFLOTRAN/paraview_processor/filters/CsvReaderFilter.py
PyFLOTRAN/paraview_processor/filters/IntegrateVariablesFilter.py
PyFLOTRAN/paraview_processor/filters/PlotOverLineFilter.py
PyFLOTRAN/paraview_processor/filters/SaveDataFilter.py
PyFLOTRAN/paraview_processor/filters/StreamTracerWithCustomSourceFilter.py
PyFLOTRAN/paraview_processor/filters/TableToPointsFilter.py
PyFLOTRAN/paraview_processor/filters/TecplotFilter.py
PyFLOTRAN/paraview_processor/filters/VtkFilter.py
PyFLOTRAN/paraview_processor/filters/XDMFFilter.py
PyFLOTRAN/paraview_processor/filters/__init__.py
PyFLOTRAN/preprocessing/BasePreprocessing.py
PyFLOTRAN/preprocessing/GidPreprocessor.py
PyFLOTRAN/preprocessing/STLFromPointCloud.py
PyFLOTRAN/preprocessing/__init__.py
PyFLOTRAN/preprocessing/DfnPreprocessor/DfnPreprocessor.py
PyFLOTRAN/preprocessing/DfnPreprocessor/Fracture.py
PyFLOTRAN/preprocessing/DfnPreprocessor/__init__.py
PyFLOTRAN/preprocessing/GiDPreprocessor/GidObject.py
PyFLOTRAN/preprocessing/GiDPreprocessor/Line.py
PyFLOTRAN/preprocessing/GiDPreprocessor/Point.py
PyFLOTRAN/preprocessing/GiDPreprocessor/Surface.py
PyFLOTRAN/preprocessing/GiDPreprocessor/_AbstractGidObject.py
PyFLOTRAN/preprocessing/GiDPreprocessor/__init__.py
PyFLOTRAN-1.5.4.dist-info/LICENSE.txt
PyFLOTRAN-1.5.4.dist-info/METADATA
PyFLOTRAN-1.5.4.dist-info/WHEEL
PyFLOTRAN-1.5.4.dist-info/top_level.txt
PyFLOTRAN-1.5.4.dist-info/RECORD
